opentelemetry/instrumentation/fastmcp/__init__.py
opentelemetry/instrumentation/fastmcp/client_instrumentor.py
opentelemetry/instrumentation/fastmcp/instrumentation.py
opentelemetry/instrumentation/fastmcp/propagation.py
opentelemetry/instrumentation/fastmcp/server_instrumentor.py
opentelemetry/instrumentation/fastmcp/transport_instrumentor.py
opentelemetry/instrumentation/fastmcp/utils.py
opentelemetry/instrumentation/fastmcp/version.py
splunk_otel_instrumentation_fastmcp-0.1.1.dist-info/METADATA
splunk_otel_instrumentation_fastmcp-0.1.1.dist-info/WHEEL
splunk_otel_instrumentation_fastmcp-0.1.1.dist-info/entry_points.txt
splunk_otel_instrumentation_fastmcp-0.1.1.dist-info/RECORD
