Metadata-Version: 2.4
Name: splunk-otel-instrumentation-fastmcp
Version: 0.1.1
Summary: Splunk OpenTelemetry instrumentation for FastMCP (Model Context Protocol)
Project-URL: Homepage, https://github.com/signalfx/splunk-otel-python-contrib
Project-URL: Repository, https://github.com/signalfx/splunk-otel-python-contrib
License-Expression: Apache-2.0
Classifier: Development Status :: 4 - Beta
Classifier: Intended Audience :: Developers
Classifier: License :: OSI Approved :: Apache Software License
Classifier: Programming Language :: Python
Classifier: Programming Language :: Python :: 3.10
Classifier: Programming Language :: Python :: 3.11
Classifier: Programming Language :: Python :: 3.12
Classifier: Programming Language :: Python :: 3.13
Requires-Python: >=3.10
Requires-Dist: opentelemetry-api~=1.38.0.dev0
Requires-Dist: opentelemetry-instrumentation~=0.59b0.dev0
Requires-Dist: opentelemetry-semantic-conventions~=0.59b0.dev0
Requires-Dist: splunk-otel-util-genai>=0.1.4
Requires-Dist: wrapt>=1.0.0
Provides-Extra: instruments
Requires-Dist: fastmcp>=2.0.0; extra == 'instruments'
Provides-Extra: test
Requires-Dist: fastmcp>=2.0.0; extra == 'test'
Requires-Dist: pytest-asyncio>=0.21.0; extra == 'test'
Requires-Dist: pytest>=7.0.0; extra == 'test'
